{"partyfacts_id":1823,"batchcomplete":"","query":{"normalized":[{"from":"Liberal_Party_(Brazil)","to":"Liberal Party (Brazil)"}],"pages":{"64268227":{"pageid":64268227,"ns":0,"title":"Liberal Party (Brazil)","langlinks":[{"lang":"ar","url":"https://ar.wikipedia.org/wiki/%D8%A7%D9%84%D8%AD%D8%B2%D8%A8_%D8%A7%D9%84%D9%84%D9%8A%D8%A8%D8%B1%D8%A7%D9%84%D9%8A_(%D8%A7%D9%84%D8%A8%D8%B1%D8%A7%D8%B2%D9%8A%D9%84)","*":"\u0627\u0644\u062d\u0632\u0628 \u0627\u0644\u0644\u064a\u0628\u0631\u0627\u0644\u064a (\u0627\u0644\u0628\u0631\u0627\u0632\u064a\u0644)"},{"lang":"fr","url":"https://fr.wikipedia.org/wiki/Parti_lib%C3%A9ral_(Br%C3%A9sil_imp%C3%A9rial)","*":"Parti lib\u00e9ral (Br\u00e9sil imp\u00e9rial)"},{"lang":"pt","url":"https://pt.wikipedia.org/wiki/Partido_Liberal_(1831)","*":"Partido Liberal (1831)"}]}}}}