{"partyfacts_id":2121,"batchcomplete":"","query":{"normalized":[{"from":"National_Democratic_and_Labour_Party","to":"National Democratic and Labour Party"}],"pages":{"918783":{"pageid":918783,"ns":0,"title":"National Democratic and Labour Party","langlinks":[{"lang":"cy","url":"https://cy.wikipedia.org/wiki/Y_Blaid_Democrataidd_Cenedlaethol_a_Llafur","*":"Y Blaid Democrataidd Cenedlaethol a Llafur"},{"lang":"es","url":"https://es.wikipedia.org/wiki/Partido_Nacional_Democr%C3%A1tico_y_Laborista","*":"Partido Nacional Democr\u00e1tico y Laborista"}]}}}}