{"partyfacts_id":3149,"batchcomplete":"","query":{"normalized":[{"from":"New_Liberal_Party_(Israel)","to":"New Liberal Party (Israel)"}],"pages":{"11220919":{"pageid":11220919,"ns":0,"title":"New Liberal Party (Israel)","langlinks":[{"lang":"cs","url":"https://cs.wikipedia.org/wiki/Nov%C3%A1_liber%C3%A1ln%C3%AD_strana_(Izrael)","*":"Nov\u00e1 liber\u00e1ln\u00ed strana (Izrael)"},{"lang":"de","url":"https://de.wikipedia.org/wiki/Miflaga_Libralit_Chadascha","*":"Miflaga Libralit Chadascha"},{"lang":"he","url":"https://he.wikipedia.org/wiki/%D7%94%D7%9E%D7%A4%D7%9C%D7%92%D7%94_%D7%9C%D7%A7%D7%99%D7%93%D7%95%D7%9D_%D7%94%D7%A8%D7%A2%D7%99%D7%95%D7%9F_%D7%94%D7%A6%D7%99%D7%95%D7%A0%D7%99","*":"\u05d4\u05de\u05e4\u05dc\u05d2\u05d4 \u05dc\u05e7\u05d9\u05d3\u05d5\u05dd \u05d4\u05e8\u05e2\u05d9\u05d5\u05df \u05d4\u05e6\u05d9\u05d5\u05e0\u05d9"}]}}}}