{"partyfacts_id":4163,"batchcomplete":"","query":{"normalized":[{"from":"Al-Islah_(Yemen)","to":"Al-Islah (Yemen)"}],"pages":{"30688815":{"pageid":30688815,"ns":0,"title":"Al-Islah (Yemen)","langlinks":[{"lang":"ar","url":"https://ar.wikipedia.org/wiki/%D8%A7%D9%84%D8%AA%D8%AC%D9%85%D8%B9_%D8%A7%D9%84%D9%8A%D9%85%D9%86%D9%8A_%D9%84%D9%84%D8%A5%D8%B5%D9%84%D8%A7%D8%AD","*":"\u0627\u0644\u062a\u062c\u0645\u0639 \u0627\u0644\u064a\u0645\u0646\u064a \u0644\u0644\u0625\u0635\u0644\u0627\u062d"},{"lang":"de","url":"https://de.wikipedia.org/wiki/Al-Islah","*":"Al-Islah"},{"lang":"es","url":"https://es.wikipedia.org/wiki/Al-Islah","*":"Al-Islah"},{"lang":"eu","url":"https://eu.wikipedia.org/wiki/Al-Islah_(Yemen)","*":"Al-Islah (Yemen)"},{"lang":"fr","url":"https://fr.wikipedia.org/wiki/Congr%C3%A8s_y%C3%A9m%C3%A9nite_pour_la_r%C3%A9forme","*":"Congr\u00e8s y\u00e9m\u00e9nite pour la r\u00e9forme"},{"lang":"hu","url":"https://hu.wikipedia.org/wiki/Iszl%C3%A1h_P%C3%A1rt","*":"Iszl\u00e1h P\u00e1rt"},{"lang":"it","url":"https://it.wikipedia.org/wiki/Al-Islah","*":"Al-Islah"},{"lang":"ja","url":"https://ja.wikipedia.org/wiki/%E3%82%A2%E3%83%AB%EF%BC%9D%E3%82%A4%E3%82%B9%E3%83%A9","*":"\u30a2\u30eb\uff1d\u30a4\u30b9\u30e9"},{"lang":"ko","url":"https://ko.wikipedia.org/wiki/%EC%95%8C%EC%9D%B4%EC%8A%AC%EB%9D%BC","*":"\uc54c\uc774\uc2ac\ub77c"},{"lang":"nb","url":"https://no.wikipedia.org/wiki/Al-Islah","*":"Al-Islah"},{"lang":"pt","url":"https://pt.wikipedia.org/wiki/Al-Islah","*":"Al-Islah"},{"lang":"ru","url":"https://ru.wikipedia.org/wiki/%D0%98%D1%81%D0%BB%D0%B0%D1%85","*":"\u0418\u0441\u043b\u0430\u0445"},{"lang":"sv","url":"https://sv.wikipedia.org/wiki/Al-Islah","*":"Al-Islah"},{"lang":"tr","url":"https://tr.wikipedia.org/wiki/El-Islah","*":"El-Islah"}]}}}}