{"partyfacts_id":4178,"batchcomplete":"","query":{"normalized":[{"from":"The_Independents_(Liechtenstein)","to":"The Independents (Liechtenstein)"}],"pages":{"38423511":{"pageid":38423511,"ns":0,"title":"The Independents (Liechtenstein)","langlinks":[{"lang":"als","url":"https://als.wikipedia.org/wiki/Die_Unabh%C3%A4ngigen_(Liechtenstein)","*":"Die Unabh\u00e4ngigen (Liechtenstein)"},{"lang":"de","url":"https://de.wikipedia.org/wiki/Die_Unabh%C3%A4ngigen_(Liechtenstein)","*":"Die Unabh\u00e4ngigen (Liechtenstein)"},{"lang":"es","url":"https://es.wikipedia.org/wiki/Los_Independientes","*":"Los Independientes"},{"lang":"fr","url":"https://fr.wikipedia.org/wiki/Les_Ind%C3%A9pendants_(Liechtenstein)","*":"Les Ind\u00e9pendants (Liechtenstein)"},{"lang":"hu","url":"https://hu.wikipedia.org/wiki/A_F%C3%BCggetlenek","*":"A F\u00fcggetlenek"},{"lang":"ie","url":"https://ie.wikipedia.org/wiki/Li_%C3%8Dndependentes_(Liechtenstein)","*":"Li \u00cdndependentes (Liechtenstein)"},{"lang":"it","url":"https://it.wikipedia.org/wiki/Gli_Indipendenti_(Liechtenstein)","*":"Gli Indipendenti (Liechtenstein)"},{"lang":"ko","url":"https://ko.wikipedia.org/wiki/%EB%8F%85%EB%A6%BD_(%EB%A6%AC%ED%9E%88%ED%85%90%EC%8A%88%ED%83%80%EC%9D%B8)","*":"\ub3c5\ub9bd (\ub9ac\ud788\ud150\uc288\ud0c0\uc778)"},{"lang":"lmo","url":"https://lmo.wikipedia.org/wiki/I_Independent_(Liechtenstein)","*":"I Independent (Liechtenstein)"},{"lang":"nl","url":"https://nl.wikipedia.org/wiki/Die_Unabh%C3%A4ngigen","*":"Die Unabh\u00e4ngigen"},{"lang":"pl","url":"https://pl.wikipedia.org/wiki/Niezale%C5%BCni_(Liechtenstein)","*":"Niezale\u017cni (Liechtenstein)"},{"lang":"ru","url":"https://ru.wikipedia.org/wiki/%D0%9D%D0%B5%D0%B7%D0%B0%D0%B2%D0%B8%D1%81%D0%B8%D0%BC%D1%8B%D0%B5_(%D0%9B%D0%B8%D1%85%D1%82%D0%B5%D0%BD%D1%88%D1%82%D0%B5%D0%B9%D0%BD)","*":"\u041d\u0435\u0437\u0430\u0432\u0438\u0441\u0438\u043c\u044b\u0435 (\u041b\u0438\u0445\u0442\u0435\u043d\u0448\u0442\u0435\u0439\u043d)"},{"lang":"uk","url":"https://uk.wikipedia.org/wiki/%D0%9D%D0%B5%D0%B7%D0%B0%D0%BB%D0%B5%D0%B6%D0%BD%D1%96_(%D0%BF%D0%B0%D1%80%D1%82%D1%96%D1%8F)","*":"\u041d\u0435\u0437\u0430\u043b\u0435\u0436\u043d\u0456 (\u043f\u0430\u0440\u0442\u0456\u044f)"}]}}}}