{"partyfacts_id":4422,"batchcomplete":"","query":{"normalized":[{"from":"National_Unification_Party_(Costa_Rica)","to":"National Unification Party (Costa Rica)"}],"pages":{"20496006":{"pageid":20496006,"ns":0,"title":"National Unification Party (Costa Rica)","langlinks":[{"lang":"es","url":"https://es.wikipedia.org/wiki/Partido_Unificaci%C3%B3n_Nacional","*":"Partido Unificaci\u00f3n Nacional"},{"lang":"it","url":"https://it.wikipedia.org/wiki/Partito_Unificazione_Nazionale","*":"Partito Unificazione Nazionale"}]}}}}