{"partyfacts_id":4467,"batchcomplete":"","query":{"normalized":[{"from":"National_Association_(South_Korea)","to":"National Association (South Korea)"}],"pages":{"49588726":{"pageid":49588726,"ns":0,"title":"National Association (South Korea)","langlinks":[{"lang":"es","url":"https://es.wikipedia.org/wiki/Asociaci%C3%B3n_Nacional_(Corea_del_Sur)","*":"Asociaci\u00f3n Nacional (Corea del Sur)"},{"lang":"ja","url":"https://ja.wikipedia.org/wiki/%E5%A4%A7%E9%9F%93%E7%8B%AC%E7%AB%8B%E4%BF%83%E6%88%90%E5%9B%BD%E6%B0%91%E4%BC%9A","*":"\u5927\u97d3\u72ec\u7acb\u4fc3\u6210\u56fd\u6c11\u4f1a"},{"lang":"ko","url":"https://ko.wikipedia.org/wiki/%EB%8C%80%ED%95%9C%EB%8F%85%EB%A6%BD%EC%B4%89%EC%84%B1%EA%B5%AD%EB%AF%BC%ED%9A%8C","*":"\ub300\ud55c\ub3c5\ub9bd\ucd09\uc131\uad6d\ubbfc\ud68c"},{"lang":"pt","url":"https://pt.wikipedia.org/wiki/Associa%C3%A7%C3%A3o_Nacional_(Coreia_do_Sul)","*":"Associa\u00e7\u00e3o Nacional (Coreia do Sul)"},{"lang":"zh","url":"https://zh.wikipedia.org/wiki/%E5%9C%8B%E6%B0%91%E6%9C%83_(1946%E5%B9%B4)","*":"\u570b\u6c11\u6703 (1946\u5e74)"}]}}}}