{"partyfacts_id":5217,"batchcomplete":"","query":{"normalized":[{"from":"National_Progressive_Front_(Syria)","to":"National Progressive Front (Syria)"}],"pages":{"2149212":{"pageid":2149212,"ns":0,"title":"National Progressive Front (Syria)","langlinks":[{"lang":"ar","url":"https://ar.wikipedia.org/wiki/%D8%A7%D9%84%D8%AC%D8%A8%D9%87%D8%A9_%D8%A7%D9%84%D9%88%D8%B7%D9%86%D9%8A%D8%A9_%D8%A7%D9%84%D8%AA%D9%82%D8%AF%D9%85%D9%8A%D8%A9_(%D8%B3%D9%88%D8%B1%D9%8A%D8%A7)","*":"\u0627\u0644\u062c\u0628\u0647\u0629 \u0627\u0644\u0648\u0637\u0646\u064a\u0629 \u0627\u0644\u062a\u0642\u062f\u0645\u064a\u0629 (\u0633\u0648\u0631\u064a\u0627)"},{"lang":"bg","url":"https://bg.wikipedia.org/wiki/%D0%9D%D0%B0%D1%86%D0%B8%D0%BE%D0%BD%D0%B0%D0%BB%D0%B5%D0%BD_%D0%BF%D1%80%D0%BE%D0%B3%D1%80%D0%B5%D1%81%D0%B8%D0%B2%D0%B5%D0%BD_%D1%84%D1%80%D0%BE%D0%BD%D1%82_(%D0%A1%D0%B8%D1%80%D0%B8%D1%8F)","*":"\u041d\u0430\u0446\u0438\u043e\u043d\u0430\u043b\u0435\u043d \u043f\u0440\u043e\u0433\u0440\u0435\u0441\u0438\u0432\u0435\u043d \u0444\u0440\u043e\u043d\u0442 (\u0421\u0438\u0440\u0438\u044f)"},{"lang":"de","url":"https://de.wikipedia.org/wiki/Nationale_Progressive_Front","*":"Nationale Progressive Front"},{"lang":"el","url":"https://el.wikipedia.org/wiki/%CE%95%CE%B8%CE%BD%CE%B9%CE%BA%CF%8C_%CE%A0%CF%81%CE%BF%CE%BF%CE%B4%CE%B5%CF%85%CF%84%CE%B9%CE%BA%CF%8C_%CE%9C%CE%AD%CF%84%CF%89%CF%80%CE%BF_(%CE%A3%CF%85%CF%81%CE%AF%CE%B1)","*":"\u0395\u03b8\u03bd\u03b9\u03ba\u03cc \u03a0\u03c1\u03bf\u03bf\u03b4\u03b5\u03c5\u03c4\u03b9\u03ba\u03cc \u039c\u03ad\u03c4\u03c9\u03c0\u03bf (\u03a3\u03c5\u03c1\u03af\u03b1)"},{"lang":"es","url":"https://es.wikipedia.org/wiki/Frente_Nacional_Progresista","*":"Frente Nacional Progresista"},{"lang":"fa","url":"https://fa.wikipedia.org/wiki/%D8%AC%D8%A8%D9%87%D9%87_%D9%85%D9%84%DB%8C_%D9%BE%DB%8C%D8%B4%D8%B1%D9%88_(%D8%B3%D9%88%D8%B1%DB%8C%D9%87)","*":"\u062c\u0628\u0647\u0647 \u0645\u0644\u06cc \u067e\u06cc\u0634\u0631\u0648 (\u0633\u0648\u0631\u06cc\u0647)"},{"lang":"fr","url":"https://fr.wikipedia.org/wiki/Front_national_progressiste","*":"Front national progressiste"},{"lang":"it","url":"https://it.wikipedia.org/wiki/Fronte_Nazionale_Progressista","*":"Fronte Nazionale Progressista"},{"lang":"pl","url":"https://pl.wikipedia.org/wiki/Narodowy_Front_Post%C4%99pu_(Syria)","*":"Narodowy Front Post\u0119pu (Syria)"},{"lang":"pt","url":"https://pt.wikipedia.org/wiki/Frente_Progressista_Nacional","*":"Frente Progressista Nacional"},{"lang":"ru","url":"https://ru.wikipedia.org/wiki/%D0%9D%D0%B0%D1%86%D0%B8%D0%BE%D0%BD%D0%B0%D0%BB%D1%8C%D0%BD%D1%8B%D0%B9_%D0%BF%D1%80%D0%BE%D0%B3%D1%80%D0%B5%D1%81%D1%81%D0%B8%D0%B2%D0%BD%D1%8B%D0%B9_%D1%84%D1%80%D0%BE%D0%BD%D1%82","*":"\u041d\u0430\u0446\u0438\u043e\u043d\u0430\u043b\u044c\u043d\u044b\u0439 \u043f\u0440\u043e\u0433\u0440\u0435\u0441\u0441\u0438\u0432\u043d\u044b\u0439 \u0444\u0440\u043e\u043d\u0442"},{"lang":"sco","url":"https://sco.wikipedia.org/wiki/Naitional_Progressive_Front_(Sirie)","*":"Naitional Progressive Front (Sirie)"},{"lang":"sv","url":"https://sv.wikipedia.org/wiki/Nationella_progressiva_fronten","*":"Nationella progressiva fronten"},{"lang":"tr","url":"https://tr.wikipedia.org/wiki/Ulusal_%C4%B0lerici_Cephe_(Suriye)","*":"Ulusal \u0130lerici Cephe (Suriye)"},{"lang":"vi","url":"https://vi.wikipedia.org/wiki/M%E1%BA%B7t_tr%E1%BA%ADn_Ti%E1%BA%BFn_b%E1%BB%99_Qu%E1%BB%91c_gia_(Syria)","*":"M\u1eb7t tr\u1eadn Ti\u1ebfn b\u1ed9 Qu\u1ed1c gia (Syria)"},{"lang":"zh","url":"https://zh.wikipedia.org/wiki/%E5%85%A8%E5%9B%BD%E8%BF%9B%E6%AD%A5%E9%98%B5%E7%BA%BF","*":"\u5168\u56fd\u8fdb\u6b65\u9635\u7ebf"}]}}}}