{"partyfacts_id":5353,"batchcomplete":"","query":{"normalized":[{"from":"National_Council_of_Nigeria_and_the_Cameroons","to":"National Council of Nigeria and the Cameroons"}],"pages":{"2368946":{"pageid":2368946,"ns":0,"title":"National Council of Nigeria and the Cameroons","langlinks":[{"lang":"ca","url":"https://ca.wikipedia.org/wiki/Consell_Nacional_de_Nig%C3%A8ria_i_els_Cameruns","*":"Consell Nacional de Nig\u00e8ria i els Cameruns"},{"lang":"de","url":"https://de.wikipedia.org/wiki/National_Council_of_Nigeria_and_the_Cameroons","*":"National Council of Nigeria and the Cameroons"},{"lang":"eo","url":"https://eo.wikipedia.org/wiki/Nacia_Konsilio_de_Nigerio_kaj_Kameruno","*":"Nacia Konsilio de Nigerio kaj Kameruno"},{"lang":"fr","url":"https://fr.wikipedia.org/wiki/Conseil_national_du_Nigeria_et_du_Cameroun","*":"Conseil national du Nigeria et du Cameroun"},{"lang":"nl","url":"https://nl.wikipedia.org/wiki/National_Council_of_Nigeria_and_the_Cameroons","*":"National Council of Nigeria and the Cameroons"},{"lang":"pt","url":"https://pt.wikipedia.org/wiki/Conselho_Nacional_da_Nig%C3%A9ria_e_Camar%C3%B5es","*":"Conselho Nacional da Nig\u00e9ria e Camar\u00f5es"},{"lang":"sv","url":"https://sv.wikipedia.org/wiki/Nationella_medborgarr%C3%A5det","*":"Nationella medborgarr\u00e5det"}]}}}}