{"partyfacts_id":5363,"batchcomplete":"","query":{"normalized":[{"from":"National_Movement_of_the_Revolution","to":"National Movement of the Revolution"}],"pages":{"25490379":{"pageid":25490379,"ns":0,"title":"National Movement of the Revolution","langlinks":[{"lang":"nl","url":"https://nl.wikipedia.org/wiki/Mouvement_national_de_la_r%C3%A9volution","*":"Mouvement national de la r\u00e9volution"},{"lang":"pl","url":"https://pl.wikipedia.org/wiki/Narodowy_Ruch_Rewolucyjny","*":"Narodowy Ruch Rewolucyjny"}]}}}}