{"partyfacts_id":571,"batchcomplete":"","query":{"normalized":[{"from":"National_Encounter_Party","to":"National Encounter Party"}],"pages":{"2659689":{"pageid":2659689,"ns":0,"title":"National Encounter Party","langlinks":[{"lang":"da","url":"https://da.wikipedia.org/wiki/National_Encounter_parti","*":"National Encounter parti"},{"lang":"es","url":"https://es.wikipedia.org/wiki/Partido_Encuentro_Nacional","*":"Partido Encuentro Nacional"},{"lang":"it","url":"https://it.wikipedia.org/wiki/Partito_Incontro_Nazionale","*":"Partito Incontro Nazionale"}]}}}}