{"partyfacts_id":6335,"batchcomplete":"","query":{"normalized":[{"from":"Conservative_Republican_Party","to":"Conservative Republican Party"}],"pages":{"33852454":{"pageid":33852454,"ns":0,"title":"Conservative Republican Party","langlinks":[{"lang":"ar","url":"https://ar.wikipedia.org/wiki/%D8%A7%D9%84%D8%AD%D8%B2%D8%A8_%D8%A7%D9%84%D8%AC%D9%85%D9%87%D9%88%D8%B1%D9%8A_%D8%A7%D9%84%D9%85%D8%AD%D8%A7%D9%81%D8%B8","*":"\u0627\u0644\u062d\u0632\u0628 \u0627\u0644\u062c\u0645\u0647\u0648\u0631\u064a \u0627\u0644\u0645\u062d\u0627\u0641\u0638"},{"lang":"pt","url":"https://pt.wikipedia.org/wiki/Partido_Republicano_Conservador","*":"Partido Republicano Conservador"}]}}}}