{"partyfacts_id":6512,"batchcomplete":"","query":{"normalized":[{"from":"Kenya_People's_Union","to":"Kenya People's Union"}],"pages":{"24809832":{"pageid":24809832,"ns":0,"title":"Kenya People's Union","langlinks":[{"lang":"es","url":"https://es.wikipedia.org/wiki/Uni%C3%B3n_Popular_de_Kenia","*":"Uni\u00f3n Popular de Kenia"},{"lang":"id","url":"https://id.wikipedia.org/wiki/Kenya_People%27s_Union","*":"Kenya People's Union"},{"lang":"sw","url":"https://sw.wikipedia.org/wiki/Kenya_People%27s_Union","*":"Kenya People's Union"}]}}}}