{"partyfacts_id":7158,"batchcomplete":"","query":{"normalized":[{"from":"Peruvian_Humanist_Party","to":"Peruvian Humanist Party"}],"pages":{"5641510":{"pageid":5641510,"ns":0,"title":"Peruvian Humanist Party","langlinks":[{"lang":"es","url":"https://es.wikipedia.org/wiki/Partido_Humanista_Peruano","*":"Partido Humanista Peruano"},{"lang":"nl","url":"https://nl.wikipedia.org/wiki/Peruviaanse_Humanistische_Partij","*":"Peruviaanse Humanistische Partij"},{"lang":"zh","url":"https://zh.wikipedia.org/wiki/%E7%A7%98%E9%B2%81%E4%BA%BA%E6%96%87%E4%B8%BB%E4%B9%89%E5%85%9A","*":"\u79d8\u9c81\u4eba\u6587\u4e3b\u4e49\u515a"}]}}}}