{"partyfacts_id":7350,"batchcomplete":"","query":{"normalized":[{"from":"New_Right_(Israel)","to":"New Right (Israel)"}],"pages":{"59516440":{"pageid":59516440,"ns":0,"title":"New Right (Israel)","langlinks":[{"lang":"ar","url":"https://ar.wikipedia.org/wiki/%D8%A7%D9%84%D9%8A%D9%85%D9%8A%D9%86_%D8%A7%D9%84%D8%AC%D8%AF%D9%8A%D8%AF_(%D8%A5%D8%B3%D8%B1%D8%A7%D8%A6%D9%8A%D9%84)","*":"\u0627\u0644\u064a\u0645\u064a\u0646 \u0627\u0644\u062c\u062f\u064a\u062f (\u0625\u0633\u0631\u0627\u0626\u064a\u0644)"},{"lang":"ca","url":"https://ca.wikipedia.org/wiki/Nova_Dreta_(Israel)","*":"Nova Dreta (Israel)"},{"lang":"de","url":"https://de.wikipedia.org/wiki/HaJamin_HeChadasch","*":"HaJamin HeChadasch"},{"lang":"eo","url":"https://eo.wikipedia.org/wiki/Nova_Dekstro_(israela_partio)","*":"Nova Dekstro (israela partio)"},{"lang":"es","url":"https://es.wikipedia.org/wiki/Nueva_Derecha_(Israel)","*":"Nueva Derecha (Israel)"},{"lang":"fr","url":"https://fr.wikipedia.org/wiki/Nouvelle_Droite_(Isra%C3%ABl)","*":"Nouvelle Droite (Isra\u00ebl)"},{"lang":"he","url":"https://he.wikipedia.org/wiki/%D7%94%D7%99%D7%9E%D7%99%D7%9F_%D7%94%D7%97%D7%93%D7%A9","*":"\u05d4\u05d9\u05de\u05d9\u05df \u05d4\u05d7\u05d3\u05e9"},{"lang":"id","url":"https://id.wikipedia.org/wiki/Kanan_Baru_(Israel)","*":"Kanan Baru (Israel)"},{"lang":"it","url":"https://it.wikipedia.org/wiki/Nuova_Destra_(Israele)","*":"Nuova Destra (Israele)"},{"lang":"nl","url":"https://nl.wikipedia.org/wiki/Nieuw_Rechts_(Isra%C3%ABl)","*":"Nieuw Rechts (Isra\u00ebl)"},{"lang":"pl","url":"https://pl.wikipedia.org/wiki/Nowa_Prawica_(Izrael)","*":"Nowa Prawica (Izrael)"},{"lang":"ru","url":"https://ru.wikipedia.org/wiki/%D0%A5%D0%B0-%D0%AF%D0%BC%D0%B8%D0%BD_%D1%85%D0%B0-%D0%A5%D0%B0%D0%B4%D0%B0%D1%88","*":"\u0425\u0430-\u042f\u043c\u0438\u043d \u0445\u0430-\u0425\u0430\u0434\u0430\u0448"},{"lang":"simple","url":"https://simple.wikipedia.org/wiki/New_Right_(Israel)","*":"New Right (Israel)"},{"lang":"sr","url":"https://sr.wikipedia.org/wiki/%D0%9D%D0%BE%D0%B2%D0%B0_%D0%B4%D0%B5%D1%81%D0%BD%D0%B8%D1%86%D0%B0_(%D0%98%D0%B7%D1%80%D0%B0%D0%B5%D0%BB)","*":"\u041d\u043e\u0432\u0430 \u0434\u0435\u0441\u043d\u0438\u0446\u0430 (\u0418\u0437\u0440\u0430\u0435\u043b)"},{"lang":"sv","url":"https://sv.wikipedia.org/wiki/Nya_h%C3%B6gern_(Israel)","*":"Nya h\u00f6gern (Israel)"},{"lang":"tr","url":"https://tr.wikipedia.org/wiki/Yeni_Sa%C4%9F_(%C4%B0srail)","*":"Yeni Sa\u011f (\u0130srail)"},{"lang":"zh","url":"https://zh.wikipedia.org/wiki/%E6%96%B0%E5%8F%B3%E7%BF%BC_(%E4%BB%A5%E8%89%B2%E5%88%97)","*":"\u65b0\u53f3\u7ffc (\u4ee5\u8272\u5217)"}]}}}}