{"partyfacts_id":8268,"batchcomplete":"","query":{"normalized":[{"from":"Freedom_Union_(Poland)","to":"Freedom Union (Poland)"}],"pages":{"1913913":{"pageid":1913913,"ns":0,"title":"Freedom Union (Poland)","langlinks":[{"lang":"ca","url":"https://ca.wikipedia.org/wiki/Uni%C3%B3_de_la_Llibertat","*":"Uni\u00f3 de la Llibertat"},{"lang":"da","url":"https://da.wikipedia.org/wiki/Frihedsunionen","*":"Frihedsunionen"},{"lang":"de","url":"https://de.wikipedia.org/wiki/Unia_Wolno%C5%9Bci","*":"Unia Wolno\u015bci"},{"lang":"es","url":"https://es.wikipedia.org/wiki/Uni%C3%B3n_de_la_Libertad","*":"Uni\u00f3n de la Libertad"},{"lang":"fr","url":"https://fr.wikipedia.org/wiki/Union_pour_la_libert%C3%A9","*":"Union pour la libert\u00e9"},{"lang":"it","url":"https://it.wikipedia.org/wiki/Unione_della_Libert%C3%A0","*":"Unione della Libert\u00e0"},{"lang":"ja","url":"https://ja.wikipedia.org/wiki/%E8%87%AA%E7%94%B1%E9%80%A3%E5%90%88_(%E3%83%9D%E3%83%BC%E3%83%A9%E3%83%B3%E3%83%89)","*":"\u81ea\u7531\u9023\u5408 (\u30dd\u30fc\u30e9\u30f3\u30c9)"},{"lang":"nl","url":"https://nl.wikipedia.org/wiki/Unia_Wolno%C5%9Bci","*":"Unia Wolno\u015bci"},{"lang":"pl","url":"https://pl.wikipedia.org/wiki/Unia_Wolno%C5%9Bci","*":"Unia Wolno\u015bci"},{"lang":"ru","url":"https://ru.wikipedia.org/wiki/%D0%A1%D0%BE%D1%8E%D0%B7_%D1%81%D0%B2%D0%BE%D0%B1%D0%BE%D0%B4%D1%8B","*":"\u0421\u043e\u044e\u0437 \u0441\u0432\u043e\u0431\u043e\u0434\u044b"},{"lang":"sv","url":"https://sv.wikipedia.org/wiki/Frihetsunionen","*":"Frihetsunionen"},{"lang":"tr","url":"https://tr.wikipedia.org/wiki/%C3%96zg%C3%BCrl%C3%BCk_Birli%C4%9Fi_partisi","*":"\u00d6zg\u00fcrl\u00fck Birli\u011fi partisi"},{"lang":"uk","url":"https://uk.wikipedia.org/wiki/%D0%A3%D0%BD%D1%96%D1%8F_%D0%A1%D0%B2%D0%BE%D0%B1%D0%BE%D0%B4%D0%B8","*":"\u0423\u043d\u0456\u044f \u0421\u0432\u043e\u0431\u043e\u0434\u0438"}]}}}}